udata_ods/__init__.py
udata_ods/harvesters.py
udata_ods/models.py
udata_ods/preview.py
udata_ods/views.py
udata_ods/migrations/2023-05-22-migrate-to-dcat-harvest.py
udata_ods/migrations/2023-07-12-remove-double-slash-resource.py
udata_ods/templates/preview.html
udata_ods/translations/udata-ods.pot
udata_ods/translations/fr/LC_MESSAGES/udata-ods.mo
udata_ods/translations/fr/LC_MESSAGES/udata-ods.po
udata_ods/translations/pt/LC_MESSAGES/udata-ods.mo
udata_ods/translations/pt/LC_MESSAGES/udata-ods.po
udata_ods-4.0.0.dist-info/LICENSE
udata_ods-4.0.0.dist-info/METADATA
udata_ods-4.0.0.dist-info/WHEEL
udata_ods-4.0.0.dist-info/entry_points.txt
udata_ods-4.0.0.dist-info/top_level.txt
udata_ods-4.0.0.dist-info/RECORD
