Metadata-Version: 2.1
Name: udata-ods
Version: 4.0.0
Summary: OpenDataSoft integration for udata
Home-page: https://github.com/opendatateam/udata-ods
Author: OpenDataTeam
Author-email: contact@opendata.team
License: AGPL
Keywords: udata harvester OpenDataSoft
Classifier: Development Status :: 3 - Alpha
Classifier: Programming Language :: Python
Classifier: Environment :: Web Environment
Classifier: Operating System :: OS Independent
Classifier: Intended Audience :: Developers
Classifier: Topic :: System :: Software Distribution
Classifier: Programming Language :: Python
Classifier: Programming Language :: Python :: 3
Classifier: Programming Language :: Python :: 3.7
Classifier: Topic :: Software Development :: Libraries :: Python Modules
Requires-Python: >=3.7
License-File: LICENSE
Requires-Dist: udata >=5.0.0
Provides-Extra: test
Requires-Dist: mock ==5.0.1 ; extra == 'test'
Requires-Dist: pytest ==7.2.1 ; extra == 'test'
Requires-Dist: pytest-flask ==1.2.0 ; extra == 'test'
Requires-Dist: pytest-sugar ==0.9.6 ; extra == 'test'
Requires-Dist: requests-mock ==1.10.0 ; extra == 'test'
